cus_stat/__init__.py
stat/__init__.py
cus_stat-0.1.dist-info/LICENSE.txt
cus_stat-0.1.dist-info/METADATA
cus_stat-0.1.dist-info/WHEEL
cus_stat-0.1.dist-info/top_level.txt
cus_stat-0.1.dist-info/RECORD
