Metadata-Version: 2.1
Name: cus-stat
Version: 0.1
Summary: not much
Home-page: UNKNOWN
Author: me
Author-email: nabila.da19@iiitmk.ac.in
License: UNKNOWN
Platform: UNKNOWN
Classifier: Programming Language :: Python :: 3
Classifier: License :: OSI Approved :: MIT License
Classifier: Operating System :: OS Independent
License-File: LICENSE.txt
